{
	"info": {
		"_postman_id": "4eb7eabe-e8e9-4277-83c7-f4a5430cb378",
		"name": "cloud-cdnd-c2-final",
		"schema": "https://schema.getpostman.com/json/collection/v2.1.0/collection.json"
	},
	"item": [
		{
			"name": "http://{{HOST}}/filteredimage?image_url=https://image.shutterstock.com/image-vector/covid19-young-women-sitting-home-600w-1687441222.jpg",
			"request": {
				"method": "GET",
				"header": [],
				"url": {
					"raw": "http://{{HOST}}/filteredimage?image_url=https://image.shutterstock.com/image-vector/covid19-young-women-sitting-home-600w-1687441222.jpg",
					"protocol": "http",
					"host": [
						"{{HOST}}"
					],
					"path": [
						"filteredimage"
					],
					"query": [
						{
							"key": "image_url",
							"value": "https://image.shutterstock.com/image-vector/covid19-young-women-sitting-home-600w-1687441222.jpg"
						}
					]
				}
			},
			"response": []
		},
		{
			"name": "http://{{HOST}}/filteredimage?image_url=https://image.shutterstock.com/image-vector/covid19-young-women-sitting-home-600w-1687441222.jpge",
			"request": {
				"method": "GET",
				"header": [],
				"url": {
					"raw": "http://{{HOST}}/filteredimage?image_url=https://image.shutterstock.com/image-vector/covid19-young-women-sitting-home-600w-1687441222.jpge",
					"protocol": "http",
					"host": [
						"{{HOST}}"
					],
					"path": [
						"filteredimage"
					],
					"query": [
						{
							"key": "image_url",
							"value": "https://image.shutterstock.com/image-vector/covid19-young-women-sitting-home-600w-1687441222.jpge"
						}
					]
				}
			},
			"response": []
		},
		{
			"name": "http://{{HOST}}/filteredimage/",
			"request": {
				"method": "GET",
				"header": [],
				"url": {
					"raw": "http://{{HOST}}/filteredImage/",
					"protocol": "http",
					"host": [
						"{{HOST}}"
					],
					"path": [
						"filteredImage",
						""
					]
				}
			},
			"response": []
		}
	],
	"event": [
		{
			"listen": "prerequest",
			"script": {
				"id": "58d3a3de-471b-49d8-89f9-b87b2e1e337a",
				"type": "text/javascript",
				"exec": [
					""
				]
			}
		},
		{
			"listen": "test",
			"script": {
				"id": "6521a04a-dd3f-4bb4-ba19-336ae167c168",
				"type": "text/javascript",
				"exec": [
					""
				]
			}
		}
	],
	"variable": [
		{
			"id": "1df3d31a-de30-494b-a3d0-f1228dd8713c",
			"key": "HOST",
			"value": "localhost:8082",
			"type": "string"
		}
	],
	"protocolProfileBehavior": {}
}